datamart_augmentation/__init__.py
datamart_augmentation/augmentation.py
datamart_augmentation-0.9.dist-info/LICENSE.txt
datamart_augmentation-0.9.dist-info/METADATA
datamart_augmentation-0.9.dist-info/NOTICE.txt
datamart_augmentation-0.9.dist-info/WHEEL
datamart_augmentation-0.9.dist-info/top_level.txt
datamart_augmentation-0.9.dist-info/RECORD
