Metadata-Version: 2.1
Name: datamart-augmentation
Version: 0.9
Summary: Data augmentation functions for Auctus
Home-page: https://gitlab.com/ViDA-NYU/auctus/auctus
Author: Remi Rampin
Author-email: remi.rampin@nyu.edu
Maintainer: Remi Rampin
Maintainer-email: remi.rampin@nyu.edu
License: Apache-2.0
Project-URL: Homepage, https://gitlab.com/ViDA-NYU/auctus/auctus
Project-URL: Source, https://gitlab.com/ViDA-NYU/auctus/auctus
Project-URL: Tracker, https://gitlab.com/ViDA-NYU/auctus/auctus/-/issues
Keywords: auctus,datamart
Platform: UNKNOWN
Classifier: Development Status :: 4 - Beta
Classifier: Intended Audience :: Science/Research
Classifier: License :: OSI Approved :: Apache Software License
Classifier: Operating System :: OS Independent
Classifier: Programming Language :: Python :: 3 :: Only
Classifier: Topic :: Scientific/Engineering :: Information Analysis
Requires-Dist: pandas
Requires-Dist: numpy
Requires-Dist: datamart-materialize (==0.9)
Requires-Dist: datamart-profiler (==0.9)
